zeusrobot/ZeusRobot.py
zeusrobot/__init__.py
zeusrobot/_zeusrobot/__init__.py
zeusrobot/_zeusrobot/zeus_common.py
zeusrobot/_zeusrobot/zeus_error.py
zeusrobot/_zeusrobot/zeus_io.py
zeusrobot/_zeusrobot/zeus_rblib.py
zeusrobot/_zeusrobot/_zeus_shared_memory/__init__.py
zeusrobot/_zeusrobot/_zeus_shared_memory/zeus_shared_memory_api.py
zeusrobot/_zeusrobot/_zeus_shared_memory/zeus_shared_memory_format.py
zeusrobot/_zeusrobot/_zeus_shared_memory/zeus_shared_memory_table.py
zeusrobot-0.0.4.dist-info/LICENSE.txt
zeusrobot-0.0.4.dist-info/METADATA
zeusrobot-0.0.4.dist-info/WHEEL
zeusrobot-0.0.4.dist-info/top_level.txt
zeusrobot-0.0.4.dist-info/RECORD
